{"_ts":[1572568179,1572612076,1572655440,1572788430,1572876586,1572920516],"_r":{"breakdown":{"html":{"bytes":[0,0,0,0,0,0],"requests":[0,0,0,0,0,0]},"js":{"bytes":[0,0,0,0,0,0],"requests":[0,0,0,0,0,0]},"css":{"bytes":[0,0,0,0,0,0],"requests":[0,0,0,0,0,0]},"image":{"bytes":[0,0,0,0,0,0],"requests":[0,0,0,0,0,0]},"flash":{"bytes":[0,0,0,0,0,0],"requests":[0,0,0,0,0,0]},"font":{"bytes":[0,0,0,0,0,0],"requests":[0,0,0,0,0,0]},"video":{"bytes":[0,0,0,0,0,0],"requests":[0,0,0,0,0,0]},"other":{"bytes":[0,0,0,0,0,0],"requests":[0,1,1,0,0,1]}},"date":[1572568179,1572612076,1572655440,1572788430,1572876586,1572920516],"domElements":[null,null,null,null,null,null],"domInteractive":[null,null,null,null,null,null],"firstPaint":[null,null,null,null,null,null],"fullyLoaded":[null,null,null,null,null,null],"id":["191101_W9_f2e350fd736763363eb6d01b3cef6342","191101_8X_f5c5fe32aeb0b864c6380ef1e67a2508","191102_AJ_1ae3e02b85832749f7372d69b1700180","191103_5X_7c38ef353740ba39d4e2088d8d622287","191104_TS_8ceabca2fbbc2d01bcf42efab0df1cff","191105_NW_e4d4956be969227c4235238bf402f0bc"],"loadTime":[null,null,null,null,null,null],"render":[null,null,null,null,null,null],"SpeedIndex":[null,null,null,null,null,null],"TTFB":[null,null,null,null,null,null],"videoFrames":[[{"_i":"ms_000000.jpg","_t":0,"_vc":100}],[{"_i":"ms_000000.jpg","_t":0,"_vc":100}],[{"_i":"ms_000000.jpg","_t":0,"_vc":100}],[{"_i":"ms_000000.jpg","_t":0,"_vc":100}],[{"_i":"ms_000000.jpg","_t":0,"_vc":100}],[{"_i":"ms_000000.jpg","_t":0,"_vc":100}]],"visualComplete":[null,null,null,null,null,null],"lighthouse":[null,null,null,null,null,null],"pagespeed":[null,null,null,null,null,null]}}